Workbook

Sheet ⚙️ Paramètres
A1: PARAMÈTRES DU PROJET — Budget EVM
A3: Nom du projet | B3: [Entrez le nom du projet ici]
A4: Chef de Projet | B4: [Nom du CP]
A5: Sponsor | B5: [Nom du Sponsor]
A6: Date de début | B6: 2026-01-01
A7: Date de fin prévue | B7: 2026-12-31
A8: Mois courant (1-12) | B8: 7 | C8: Le mois pour lequel calculer les KPIs
A9: Devise | B9: €
A10: Méthodologie | B10: PMBOK 7

Sheet 📋 Work Packages & PV
A1: WORK PACKAGES & VALEUR PLANIFIÉE (PV) — Saisir les cellules bleues
A3: # | B3: Phase | C3: Work Package | D3: Responsable | E3: BAC (€) | F3: Jan | G3: Fév | H3: Mar | I3: Avr | J3: Mai | K3: Jun | L3: Jul | M3: Aoû | N3: Sep | O3: Oct | P3: Nov | Q3: Déc
A4: WP1 | B4: Phase 1 — Init. | C4: Initialisation & Cadrage | D4: Chef de Projet | E4: 25000 | F4: 1000 | G4: 2000 | H4: 3000 | I4: 4000 | J4: 5000 | K4: 6000 | L4: 7000 | M4: 8000 | N4: 9500 | O4: 11000 | P4: 13000 | Q4: 15000
A5: WP2 | B5: Phase 1 — Init. | C5: Planification détaillée | D5: Chef de Projet | E5: 15000 | F5: 0 | G5: 1500 | H5: 3000 | I5: 4500 | J5: 6000 | K5: 7500 | L5: 9000 | M5: 10500 | N5: 12000 | O5: 13500 | P5: 15000 | Q5: 15000
A6: WP3 | B6: Phase 2 — Analyse | C6: Audit infrastructure | D6: Architecte SI | E6: 30000 | F6: 0 | G6: 0 | H6: 3000 | I6: 6000 | J6: 10500 | K6: 15000 | L6: 19500 | M6: 24000 | N6: 27000 | O6: 30000 | P6: 30000 | Q6: 30000
A7: WP4 | B7: Phase 2 — Analyse | C7: Reverse engineering apps | D7: Architecte Sol. | E7: 20000 | F7: 0 | G7: 0 | H7: 0 | I7: 3000 | J7: 6000 | K7: 10000 | L7: 13000 | M7: 16000 | N7: 18000 | O7: 20000 | P7: 20000 | Q7: 20000
A8: WP5 | B8: Phase 3 — Conception | C8: Architecture cible | D8: Architecte Inf. | E8: 40000 | F8: 0 | G8: 0 | H8: 0 | I8: 0 | J8: 4000 | K8: 10000 | L8: 16000 | M8: 24000 | N8: 30000 | O8: 36000 | P8: 40000 | Q8: 40000
A9: WP6 | B9: Phase 3 — Conception | C9: Conception SSO & HA | D9: Expert Sécurité | E9: 25000 | F9: 0 | G9: 0 | H9: 0 | I9: 0 | J9: 0 | K9: 3750 | L9: 8750 | M9: 13750 | N9: 18750 | O9: 22500 | P9: 25000 | Q9: 25000
A10: WP7 | B10: Phase 4 — Déploiement | C10: Migration production | D10: Admin Système | E10: 55000 | F10: 0 | G10: 0 | H10: 0 | I10: 0 | J10: 0 | K10: 0 | L10: 5500 | M10: 16500 | N10: 27500 | O10: 38500 | P10: 49500 | Q10: 55000
A11: WP8 | B11: Phase 5 — Recette | C11: Tests & validation | D11: Chef de Projet | E11: 35000 | F11: 0 | G11: 0 | H11: 0 | I11: 0 | J11: 0 | K11: 0 | L11: 0 | M11: 3500 | N11: 10500 | O11: 21000 | P11: 29750 | Q11: 35000
C12: TOTAL PV | E12: =SUM(E4:E11) | F12: =SUM(F4:F11) | G12: =SUM(G4:G11) | H12: =SUM(H4:H11) | I12: =SUM(I4:I11) | J12: =SUM(J4:J11) | K12: =SUM(K4:K11) | L12: =SUM(L4:L11) | ... Q12: =SUM(Q4:Q11)

Sheet 📥 EV & AC (Réalisé)
A1: SAISIE MENSUELLE — EV (Valeur Acquise) & AC (Coût Réel)
A2: ▼ PARTIE 1 : EV — Earned Value (Valeur Acquise) — Saisissez le cumul réalisé chaque mois pour chaque WP
A3: # | B3: Phase | C3: Work Package | D3: Resp. | E3: BAC € | F3: Jan | G3: Fév | H3: Mar | I3: Avr | J3: Mai | K3: Jun | L3: Jul | M3: Aoû | N3: Sep | O3: Oct | P3: Nov | Q3: Déc
A4: WP1 | B4: Phase 1 — Init. | C4: EV — Initialisation & Cadrage | D4: Chef de Projet | E4: 25000 | F4: 0 | G4: 0 | H4: 0 | I4: 0 | J4: 3750 | K4: 7500 | L4: 11250 | M4: 0 | N4: 0 | O4: 0 | P4: 0 | Q4: 0
A5: WP2 | B5: Phase 1 — Init. | C5: EV — Planification détaillée | D5: Chef de Projet | E5: 15000 | F5: 0 | G5: 0 | H5: 0 | I5: 0 | J5: 2250 | K5: 4500 | L5: 6750 | M5: 0 | N5: 0 | O5: 0 | P5: 0 | Q5: 0
A6: WP3 | B6: Phase 2 — Analyse | C6: EV — Audit infrastructure | D6: Architecte SI | E6: 30000 | F6: 0 | G6: 0 | H6: 0 | I6: 0 | J6: 4500 | K6: 9000 | L6: 13500 | M6: 0 | N6: 0 | O6: 0 | P6: 0 | Q6: 0
A7: WP4 | B7: Phase 2 — Analyse | C7: EV — Reverse engineering apps | D7: Architecte Sol. | E7: 20000 | F7: 0 | G7: 0 | H7: 0 | I7: 0 | J7: 3000 | K7: 6000 | L7: 9000 | M7: 0 | N7: 0 | O7: 0 | P7: 0 | Q7: 0
A8: WP5 | B8: Phase 3 — Conception | C8: EV — Architecture cible | D8: Architecte Inf. | E8: 40000 | F8: 0 | G8: 0 | H8: 0 | I8: 0 | J8: 6000 | K8: 12000 | L8: 18000 | M8: 0 | N8: 0 | O8: 0 | P8: 0 | Q8: 0
A9: WP6 | B9: Phase 3 — Conception | C9: EV — Conception SSO & HA | D9: Expert Sécurité | E9: 25000 | F9: 0 | G9: 0 | H9: 0 | I9: 0 | J9: 3750 | K9: 7500 | L9: 11250 | M9: 0 | N9: 0 | O9: 0 | P9: 0 | Q9: 0
A10: WP7 | B10: Phase 4 — Déploiement | C10: EV — Migration production | D10: Admin Système | E10: 55000 | F10: 0 | G10: 0 | H10: 0 | I10: 0 | J10: 8250 | K10: 16500 | L10: 24750 | M10: 0 | N10: 0 | O10: 0 | P10: 0 | Q10: 0
A11: WP8 | B11: Phase 5 — Recette | C11: EV — Tests & validation | D11: Chef de Projet | E11: 35000 | F11: 0 | G11: 0 | H11: 0 | I11: 0 | J11: 5250 | K11: 10500 | L11: 15750 | M11: 0 | N11: 0 | O11: 0 | P11: 0 | Q11: 0
C12: TOTAL EV | E12: =SUM(E4:E11) | F12: =SUM(F4:F11) | G12: =SUM(G4:G11) | H12: =SUM(H4:H11) | I12: =SUM(I4:I11) | J12: =SUM(J4:J11) | K12: =SUM(K4:K11) | L12: =SUM(L4:L11) | ... Q12: =SUM(Q4:Q11)
A14: ▼ PARTIE 2 : AC — Actual Cost (Coût Réel) — Saisissez les coûts réels engagés chaque mois
A15: # | B15: Phase | C15: Work Package | D15: Resp. | E15: BAC € | F15: Jan | G15: Fév | H15: Mar | I15: Avr | J15: Mai | K15: Jun | L15: Jul | M15: Aoû | N15: Sep | O15: Oct | P15: Nov | Q15: Déc
A16: WP1 | B16: Phase 1 — Init. | C16: AC — Initialisation & Cadrage | D16: Chef de Projet | E16: 25000 | F16: 0 | G16: 0 | H16: 0 | I16: 0 | J16: 4500 | K16: 9000 | L16: 13750 | M16: 0 | N16: 0 | O16: 0 | P16: 0 | Q16: 0
A17: WP2 | B17: Phase 1 — Init. | C17: AC — Planification détaillée | D17: Chef de Projet | E17: 15000 | F17: 0 | G17: 0 | H17: 0 | I17: 0 | J17: 2700 | K17: 5400 | L17: 8250 | M17: 0 | N17: 0 | O17: 0 | P17: 0 | Q17: 0
A18: WP3 | B18: Phase 2 — Analyse | C18: AC — Audit infrastructure | D18: Architecte SI | E18: 30000 | F18: 0 | G18: 0 | H18: 0 | I18: 0 | J18: 5400 | K18: 10800 | L18: 16500 | M18: 0 | N18: 0 | O18: 0 | P18: 0 | Q18: 0
A19: WP4 | B19: Phase 2 — Analyse | C19: AC — Reverse engineering apps | D19: Architecte Sol. | E19: 20000 | F19: 0 | G19: 0 | H19: 0 | I19: 0 | J19: 3600 | K19: 7200 | L19: 11000 | M19: 0 | N19: 0 | O19: 0 | P19: 0 | Q19: 0
A20: WP5 | B20: Phase 3 — Conception | C20: AC — Architecture cible | D20: Architecte Inf. | E20: 40000 | F20: 0 | G20: 0 | H20: 0 | I20: 0 | J20: 7200 | K20: 14400 | L20: 22000 | M20: 0 | N20: 0 | O20: 0 | P20: 0 | Q20: 0
A21: WP6 | B21: Phase 3 — Conception | C21: AC — Conception SSO & HA | D21: Expert Sécurité | E21: 25000 | F21: 0 | G21: 0 | H21: 0 | I21: 0 | J21: 4500 | K21: 9000 | L21: 13750 | M21: 0 | N21: 0 | O21: 0 | P21: 0 | Q21: 0
A22: WP7 | B22: Phase 4 — Déploiement | C22: AC — Migration production | D22: Admin Système | E22: 55000 | F22: 0 | G22: 0 | H22: 0 | I22: 0 | J22: 9900 | K22: 19800 | L22: 30250 | M22: 0 | N22: 0 | O22: 0 | P22: 0 | Q22: 0
A23: WP8 | B23: Phase 5 — Recette | C23: AC — Tests & validation | D23: Chef de Projet | E23: 35000 | F23: 0 | G23: 0 | H23: 0 | I23: 0 | J23: 6300 | K23: 12600 | L23: 19250 | M23: 0 | N23: 0 | O23: 0 | P23: 0 | Q23: 0
C24: TOTAL AC | E24: =SUM(E16:E23) | F24: =SUM(F16:F23) | G24: =SUM(G16:G23) | H24: =SUM(H16:H23) | I24: =SUM(I16:I23) | J24: =SUM(J16:J23) | K24: =SUM(K16:K23) | L24: =SUM(L16:L23) | ... Q24: =SUM(Q16:Q23)

Sheet 📊 Dashboard EVM
A1: TABLEAU DE BORD EVM — EARNED VALUE MANAGEMENT
A2: Les indicateurs se calculent automatiquement. Modifiez le mois en B5 pour analyser une période spécifique.
A5: 📅 Mois de référence (1=Jan … 12=Déc) : | B5: 7 | C5: ← Modifier ce chiffre
A7: INDICATEURS PRINCIPAUX
A8: BAC | B8: PV | C8: EV | D8: AC | E8: CV | F8: SV | G8: CPI | H8: SPI
A9: =SUM('📋 Work Packages & PV'!E4:E11) | B9: =INDEX('📋 Work Packages & PV'!F12:Q12,1,$B$5) | C9: =INDEX('📥 EV & AC (Réalisé)'!F12:Q12,1,$B$5) | D9: =INDEX('📥 EV & AC (Réalisé)'!F24:Q24,1,$B$5) | E9: =INDEX('📥 EV & AC (Réalisé)'!F12:Q12,1,$B$5)-INDEX('📥 EV & AC (Réalisé)'!F24:Q24,1,$B$5) | F9: =INDEX('📥 EV & AC (Réalisé)'!F12:Q12,1,$B$5)-INDEX('📋 Work Packages & PV'!F12:Q12,1,$B$5) | G9: =IFERROR((INDEX('📥 EV & AC (Réalisé)'!F12:Q12,1,$B$5))/(INDEX('📥 EV & AC (Réalisé)'!F24:Q24,1,$B$5)),0) | H9: =IFERROR((INDEX('📥 EV & AC (Réalisé)'!F12:Q12,1,$B$5))/(INDEX('📋 Work Packages & PV'!F12:Q12,1,$B$5)),0)
A10: Budget at Completion | B10: Planned Value | C10: Earned Value | D10: Actual Cost | E10: Cost Variance | F10: Schedule Variance | G10: Cost Perf. Index | H10: Schedule Perf. Index
A13: INDICATEURS AVANCÉS & PRÉVISIONS
A14: Indicateur | B14: Formule | C14: Valeur | D14: Interprétation | E14: Statut
A15: EAC — Estimate at Completion | B15: BAC ÷ CPI | C15: =IFERROR(A9/G9,0) | D15: Coût final estimé si tendance continue | E15: =IF(C15<=A9,"✅ Dans le budget","🔴 Dépassement")
A16: ETC — Estimate to Complete | B16: EAC − AC | C16: =IFERROR(A15-D9,0) | D16: Montant restant à dépenser | E16: ="—"
A17: VAC — Variance at Completion | B17: BAC − EAC | C17: =IFERROR(A9-A15,0) | D17: Dépassement (−) ou économie (+) prévue | E17: =IF(C17>=0,"💚 Économie","🔴 Dépassement")
A18: TCPI — To Complete Perf. Index | B18: (BAC−EV)÷(BAC−AC) | C18: =IFERROR((A9-C9)/(A9-D9),0) | D18: Efficacité requise pour finir dans le budget | E18: =IF(C18<=1,"✅ Réaliste","⚠️ Objectif difficile")
A19: % Avancement réel (EV) | B19: EV ÷ BAC | C19: =IFERROR(C9/A9,0) | D19: Part du budget correspondant au travail fait | E19: =IF(C19>=C20,"✅ En avance","🟡 En retard")
A20: % Avancement prévu (PV) | B20: PV ÷ BAC | C20: =IFERROR(B9/A9,0) | D20: Part du budget qui devrait être atteinte | E20: =TEXT(C20,"0.0%")&" planifié"
A21: Dépassement budgétaire | B21: (AC−EV)÷EV | C21: =IFERROR((D9-C9)/C9,0) | D21: Surcoût relatif par rapport à la valeur acquise | E21: =IF(C21<=0,"✅ Sous coût","🔴 Surcoût")
A24: SUIVI MENSUEL — PV / EV / AC / CPI / SPI
A25: Mois | B25: PV Cumulé € | C25: EV Cumulé € | D25: AC Cumulé € | E25: CV € | F25: SV € | G25: CPI | H25: SPI
A26: Jan | B26: =SUM('📋 Work Packages & PV'!F12:F12) | C26: =SUM('📥 EV & AC (Réalisé)'!F12:F12) | D26: =SUM('📥 EV & AC (Réalisé)'!F24:F24) | E26: =C26-D26 | F26: =C26-B26 | G26: =IFERROR(C26/D26,0) | H26: =IFERROR(C26/B26,0)
A27: Fév | B27: =SUM('📋 Work Packages & PV'!F12:G12) | C27: =SUM('📥 EV & AC (Réalisé)'!F12:G12) | D27: =SUM('📥 EV & AC (Réalisé)'!F24:G24) | E27: =C27-D27 | F27: =C27-B27 | G27: =IFERROR(C27/D27,0) | H27: =IFERROR(C27/B27,0)
A28: Mar | B28: =SUM('📋 Work Packages & PV'!F12:H12) | C28: =SUM('📥 EV & AC (Réalisé)'!F12:H12) | D28: =SUM('📥 EV & AC (Réalisé)'!F24:H24) | E28: =C28-D28 | F28: =C28-B28 | G28: =IFERROR(C28/D28,0) | H28: =IFERROR(C28/B28,0)
A29: Avr | B29: =SUM('📋 Work Packages & PV'!F12:I12) | C29: =SUM('📥 EV & AC (Réalisé)'!F12:I12) | D29: =SUM('📥 EV & AC (Réalisé)'!F24:I24) | E29: =C29-D29 | F29: =C29-B29 | G29: =IFERROR(C29/D29,0) | H29: =IFERROR(C29/B29,0)
A30: Mai | B30: =SUM('📋 Work Packages & PV'!F12:J12) | C30: =SUM('📥 EV & AC (Réalisé)'!F12:J12) | D30: =SUM('📥 EV & AC (Réalisé)'!F24:J24) | E30: =C30-D30 | F30: =C30-B30 | G30: =IFERROR(C30/D30,0) | H30: =IFERROR(C30/B30,0)
A31: Jun | B31: =SUM('📋 Work Packages & PV'!F12:K12) | C31: =SUM('📥 EV & AC (Réalisé)'!F12:K12) | D31: =SUM('📥 EV & AC (Réalisé)'!F24:K24) | E31: =C31-D31 | F31: =C31-B31 | G31: =IFERROR(C31/D31,0) | H31: =IFERROR(C31/B31,0)
A32: Jul | B32: =SUM('📋 Work Packages & PV'!F12:L12) | C32: =SUM('📥 EV & AC (Réalisé)'!F12:L12) | D32: =SUM('📥 EV & AC (Réalisé)'!F24:L24) | E32: =C32-D32 | F32: =C32-B32 | G32: =IFERROR(C32/D32,0) | H32: =IFERROR(C32/B32,0)
A33: Aoû | B33: =SUM('📋 Work Packages & PV'!F12:M12) | C33: =SUM('📥 EV & AC (Réalisé)'!F12:M12) | D33: =SUM('📥 EV & AC (Réalisé)'!F24:M24) | E33: =C33-D33 | F33: =C33-B33 | G33: =IFERROR(C33/D33,0) | H33: =IFERROR(C33/B33,0)
A34: Sep | B34: =SUM('📋 Work Packages & PV'!F12:N12) | C34: =SUM('📥 EV & AC (Réalisé)'!F12:N12) | D34: =SUM('📥 EV & AC (Réalisé)'!F24:N24) | E34: =C34-D34 | F34: =C34-B34 | G34: =IFERROR(C34/D34,0) | H34: =IFERROR(C34/B34,0)
A35: Oct | B35: =SUM('📋 Work Packages & PV'!F12:O12) | C35: =SUM('📥 EV & AC (Réalisé)'!F12:O12) | D35: =SUM('📥 EV & AC (Réalisé)'!F24:O24) | E35: =C35-D35 | F35: =C35-B35 | G35: =IFERROR(C35/D35,0) | H35: =IFERROR(C35/B35,0)
A36: Nov | B36: =SUM('📋 Work Packages & PV'!F12:P12) | C36: =SUM('📥 EV & AC (Réalisé)'!F12:P12) | D36: =SUM('📥 EV & AC (Réalisé)'!F24:P24) | E36: =C36-D36 | F36: =C36-B36 | G36: =IFERROR(C36/D36,0) | H36: =IFERROR(C36/B36,0)
A37: Déc | B37: =SUM('📋 Work Packages & PV'!F12:Q12) | C37: =SUM('📥 EV & AC (Réalisé)'!F12:Q12) | D37: =SUM('📥 EV & AC (Réalisé)'!F24:Q24) | E37: =C37-D37 | F37: =C37-B37 | G37: =IFERROR(C37/D37,0) | H37: =IFERROR(C37/B37,0)

Sheet 📈 Courbe S
A1: COURBES S — PV / EV / AC / EAC (Évolution cumulée sur 12 mois)
A2: Mois | B2: PV Cumulé | C2: EV Cumulé | D2: AC Cumulé | E2: EAC
A3: Jan | B3: ='📊 Dashboard EVM'!B26 | C3: ='📊 Dashboard EVM'!C26 | D3: ='📊 Dashboard EVM'!D26 | E3: =IFERROR((SUM('📋 Work Packages & PV'!E4:E11))/('📊 Dashboard EVM'!C26/'📊 Dashboard EVM'!D26),0)
A4: Fév | B4: ='📊 Dashboard EVM'!B27 | C4: ='📊 Dashboard EVM'!C27 | D4: ='📊 Dashboard EVM'!D27 | E4: =IFERROR((SUM('📋 Work Packages & PV'!E4:E11))/('📊 Dashboard EVM'!C27/'📊 Dashboard EVM'!D27),0)
A5: Mar | B5: ='📊 Dashboard EVM'!B28 | C5: ='📊 Dashboard EVM'!C28 | D5: ='📊 Dashboard EVM'!D28 | E5: =IFERROR((SUM('📋 Work Packages & PV'!E4:E11))/('📊 Dashboard EVM'!C28/'📊 Dashboard EVM'!D28),0)
A6: Avr | B6: ='📊 Dashboard EVM'!B29 | C6: ='📊 Dashboard EVM'!C29 | D6: ='📊 Dashboard EVM'!D29 | E6: =IFERROR((SUM('📋 Work Packages & PV'!E4:E11))/('📊 Dashboard EVM'!C29/'📊 Dashboard EVM'!D29),0)
A7: Mai | B7: ='📊 Dashboard EVM'!B30 | C7: ='📊 Dashboard EVM'!C30 | D7: ='📊 Dashboard EVM'!D30 | E7: =IFERROR((SUM('📋 Work Packages & PV'!E4:E11))/('📊 Dashboard EVM'!C30/'📊 Dashboard EVM'!D30),0)
A8: Jun | B8: ='📊 Dashboard EVM'!B31 | C8: ='📊 Dashboard EVM'!C31 | D8: ='📊 Dashboard EVM'!D31 | E8: =IFERROR((SUM('📋 Work Packages & PV'!E4:E11))/('📊 Dashboard EVM'!C31/'📊 Dashboard EVM'!D31),0)
A9: Jul | B9: ='📊 Dashboard EVM'!B32 | C9: ='📊 Dashboard EVM'!C32 | D9: ='📊 Dashboard EVM'!D32 | E9: =IFERROR((SUM('📋 Work Packages & PV'!E4:E11))/('📊 Dashboard EVM'!C32/'📊 Dashboard EVM'!D32),0)
A10: Aoû | B10: ='📊 Dashboard EVM'!B33 | C10: ='📊 Dashboard EVM'!C33 | D10: ='📊 Dashboard EVM'!D33 | E10: =IFERROR((SUM('📋 Work Packages & PV'!E4:E11))/('📊 Dashboard EVM'!C33/'📊 Dashboard EVM'!D33),0)
A11: Sep | B11: ='📊 Dashboard EVM'!B34 | C11: ='📊 Dashboard EVM'!C34 | D11: ='📊 Dashboard EVM'!D34 | E11: =IFERROR((SUM('📋 Work Packages & PV'!E4:E11))/('📊 Dashboard EVM'!C34/'📊 Dashboard EVM'!D34),0)
A12: Oct | B12: ='📊 Dashboard EVM'!B35 | C12: ='📊 Dashboard EVM'!C35 | D12: ='📊 Dashboard EVM'!D35 | E12: =IFERROR((SUM('📋 Work Packages & PV'!E4:E11))/('📊 Dashboard EVM'!C35/'📊 Dashboard EVM'!D35),0)
A13: Nov | B13: ='📊 Dashboard EVM'!B36 | C13: ='📊 Dashboard EVM'!C36 | D13: ='📊 Dashboard EVM'!D36 | E13: =IFERROR((SUM('📋 Work Packages & PV'!E4:E11))/('📊 Dashboard EVM'!C36/'📊 Dashboard EVM'!D36),0)
A14: Déc | B14: ='📊 Dashboard EVM'!B37 | C14: ='📊 Dashboard EVM'!C37 | D14: ='📊 Dashboard EVM'!D37 | E14: =IFERROR((SUM('📋 Work Packages & PV'!E4:E11))/('📊 Dashboard EVM'!C37/'📊 Dashboard EVM'!D37),0)

Sheet 📖 Tuto & Définitions
A1: GUIDE D'UTILISATION & DÉFINITIONS — PMO AI Studio
A3: DÉFINITIONS EVM — Earned Value Management
A4: EVM | B4: Méthode d'analyse de performance projet intégrant scope, coût et délai en une seule mesure objective.
A5: BAC — Budget at Completion | B5: Budget total approuvé pour l'ensemble du projet. C'est votre référence budgétaire.
A6: PV — Planned Value (Valeur Planifiée) | B6: Montant du travail qui DEVRAIT être réalisé à une date donnée selon le planning.
A7: EV — Earned Value (Valeur Acquise) | B7: Valeur monétaire du travail RÉELLEMENT accompli. EV = % avancement × BAC du WP.
A8: AC — Actual Cost (Coût Réel) | B8: Montant réellement DÉPENSÉ pour accomplir le travail à ce jour.
A9: CV — Cost Variance | B9: Variance de coût = EV − AC. Positif = économie. Négatif = dépassement.
A10: SV — Schedule Variance | B10: Variance de délai = EV − PV. Positif = en avance. Négatif = en retard.
A11: CPI — Cost Performance Index | B11: Efficacité coût = EV ÷ AC. >1 = efficace (sous budget). <1 = dépassement.
A12: SPI — Schedule Performance Index | B12: Efficacité planning = EV ÷ PV. >1 = en avance. <1 = en retard.
A13: EAC — Estimate at Completion | B13: Prévision du coût total final = BAC ÷ CPI. Si CPI=0.85 → EAC = BAC ÷ 0.85.
A14: ETC — Estimate to Complete | B14: Coût restant pour terminer = EAC − AC.
A15: VAC — Variance at Completion | B15: Écart final = BAC − EAC. Négatif = dépassement prévu. Positif = économie prévue.
A16: TCPI — To Complete Performance Index | B16: Efficacité requise sur le reste = (BAC−EV) ÷ (BAC−AC). >1 = doit mieux faire.
A18: GUIDE D'UTILISATION — ÉTAPES
A19: Étape 1 — Paramètres | B19: Renseignez l'onglet ⚙️ Paramètres avec le nom du projet, CP, dates.
A20: Étape 2 — Work Packages | B20: Dans 📋 Work Packages & PV : entrez le BAC de chaque WP et la distribution mensuelle prévue (PV).
A21: Étape 3 — EV mensuel | B21: Dans 📥 EV & AC : chaque mois, entrez la valeur cumulée acquise (EV) pour chaque WP.
A22: Étape 4 — AC mensuel | B22: Dans le même onglet, entrez les coûts réels cumulés (AC) pour chaque WP.
A23: Étape 5 — Dashboard | B23: Dans 📊 Dashboard EVM : changez le mois en B5 pour analyser la période souhaitée.
A24: Étape 6 — Courbe S | B24: L'onglet 📈 Courbe S se met à jour automatiquement avec le graphique.
A25: Interprétation CPI | B25: CPI = 0.85 → pour chaque euro dépensé, seulement 0.85€ de valeur est produite.
A26: Interprétation TCPI | B26: TCPI > 1.2 → très difficile de terminer dans le budget. Envisager une rebaseline.
A28: 💡 Cellules BLEUES = à saisir | Cellules NOIRES = formules automatiques | Ne pas modifier les formules
